{
    "baselines": [
        {
            "blob": "QkfsgzjXAzBCcI9DOOBQEkKMkYs42slK",
            "detector": "H3"
        },
        {
            "blob": "Qkfsg7fqgxxCcI9Dt+LjskKMkYu37/vg",
            "detector": "H1"
        },
        {
            "blob": "Qkfsg7hqQEpCcI9DuGHLFEKMkYu4ZucL",
            "detector": "L1"
        },
        {
            "blob": "Qkfsg7cDfTdCcI9DtxA3KEKMkYu29BBw",
            "detector": "L3"
        },
        {
            "blob": "Qkfsg7vjHTRCcI9Du+MbGkKMkYu74yig",
            "detector": "L5"
        }
    ],
    "commit": "4f3429463afbded239d463967ff3ac5de70d15d9",
    "encoding": "base64",
    "format": ">ff",
    "signals": [
        {
            "blob": "Qbk12j8yv7dCCKoyPzFkeg==",
            "detector": "H3",
            "isotope": "Ar40"
        },
        {
            "blob": "Qbk12rcBbBlCCKoyNwUxTA==",
            "detector": "H1",
            "isotope": "Ar39"
        },
        {
            "blob": "Qbk12jnDN7VCCKoyOcMsFA==",
            "detector": "L1",
            "isotope": "Ar38"
        },
        {
            "blob": "Qbk12rb2v2ZCCKoytr5sDA==",
            "detector": "L3",
            "isotope": "Ar37"
        },
        {
            "blob": "Qbk12rubKkZCCKoyu5txNQ==",
            "detector": "L5",
            "isotope": "Ar36"
        }
    ],
    "sniffs": [
        {
            "blob": null,
            "detector": "H3",
            "isotope": "Ar40"
        },
        {
            "blob": null,
            "detector": "H1",
            "isotope": "Ar39"
        },
        {
            "blob": null,
            "detector": "L1",
            "isotope": "Ar38"
        },
        {
            "blob": null,
            "detector": "L3",
            "isotope": "Ar37"
        },
        {
            "blob": null,
            "detector": "L5",
            "isotope": "Ar36"
        }
    ]
}