{
    "Ax": {
        "error": 1.8798570395510605e-07,
        "error_type": "SEM",
        "filter_outliers_dict": {
            "filter_outliers": false,
            "iterations": 1,
            "std_devs": 2
        },
        "fit": "average",
        "value": -0.00017464288490374343
    },
    "H2": {
        "error": 1.2896872128089403e-07,
        "error_type": "SEM",
        "filter_outliers_dict": {
            "filter_outliers": true,
            "iterations": 1,
            "std_devs": 2
        },
        "fit": "average",
        "value": -0.00018959662389596822
    },
    "H4": {
        "error": 1.5162397022790007e-07,
        "error_type": "SEM",
        "filter_outliers_dict": {
            "filter_outliers": true,
            "iterations": 1,
            "std_devs": 2
        },
        "fit": "average",
        "value": -4.789859125333333e-05
    },
    "L2": {
        "error": 9.838113116246335e-08,
        "error_type": "SEM",
        "filter_outliers_dict": {
            "filter_outliers": true,
            "iterations": 1,
            "std_devs": 2
        },
        "fit": "average",
        "value": -6.357994564604492e-06
    },
    "L4": {
        "error": 1.3063945294843619e-10,
        "error_type": "SEM",
        "filter_outliers_dict": {
            "filter_outliers": false,
            "iterations": 1,
            "std_devs": 2
        },
        "fit": "average",
        "value": 3.200000000000001e-10
    }
}