{
    "Ax": {
        "error": 1.7186429945118106e-07,
        "error_type": "SEM",
        "filter_outliers_dict": {
            "filter_outliers": false,
            "iterations": 1,
            "std_devs": 2
        },
        "fit": "average",
        "value": -0.00017649198226062082
    },
    "H2": {
        "error": 1.4590318781872807e-07,
        "error_type": "SEM",
        "filter_outliers_dict": {
            "filter_outliers": true,
            "iterations": 1,
            "std_devs": 2
        },
        "fit": "average",
        "value": -0.00019195329241500947
    },
    "H4": {
        "error": 1.4137180160392371e-07,
        "error_type": "SEM",
        "filter_outliers_dict": {
            "filter_outliers": true,
            "iterations": 1,
            "std_devs": 2
        },
        "fit": "average",
        "value": -4.734222290714286e-05
    },
    "L2": {
        "error": 1.5906012925131562e-07,
        "error_type": "SEM",
        "filter_outliers_dict": {
            "filter_outliers": true,
            "iterations": 1,
            "std_devs": 2
        },
        "fit": "average",
        "value": -4.319793013219805e-06
    },
    "L4": {
        "error": 1.321855357935046e-10,
        "error_type": "SEM",
        "filter_outliers_dict": {
            "filter_outliers": false,
            "iterations": 1,
            "std_devs": 2
        },
        "fit": "average",
        "value": 3.733333333333335e-10
    }
}