{
    "Ar36": {
        "error": 2.463307977985302e-07,
        "error_type": "",
        "fit": "previous",
        "references": [
            {
                "exclude": false,
                "record_id": "ba-01-n-8631"
            }
        ],
        "value": 2.600339738402513e-06
    },
    "Ar37": {
        "error": 2.4124049824369637e-07,
        "error_type": "",
        "fit": "previous",
        "references": [
            {
                "exclude": false,
                "record_id": "ba-01-n-8631"
            }
        ],
        "value": -5.323530203561126e-07
    },
    "Ar38": {
        "error": 2.09574212794727e-07,
        "error_type": "",
        "fit": "previous",
        "references": [
            {
                "exclude": false,
                "record_id": "ba-01-n-8631"
            }
        ],
        "value": -1.2310311161970948e-05
    },
    "Ar39": {
        "error": 3.0360774407698807e-07,
        "error_type": "",
        "fit": "previous",
        "references": [
            {
                "exclude": false,
                "record_id": "ba-01-n-8631"
            }
        ],
        "value": 1.2204018964809067e-06
    },
    "Ar40": {
        "error": 2.2845601473190744e-06,
        "error_type": "",
        "fit": "previous",
        "references": [
            {
                "exclude": false,
                "record_id": "ba-01-n-8631"
            }
        ],
        "value": 3.425467578657644e-05
    }
}