{
    "Ar36": {
        "error": 1.7527857385168e-08,
        "error_type": "",
        "fit": "previous",
        "references": [
            {
                "exclude": false,
                "record_id": "ba-01-n-9096"
            }
        ],
        "value": 4.5286623900277644e-07
    },
    "Ar37": {
        "error": 2.2915972232062028e-07,
        "error_type": "",
        "fit": "previous",
        "references": [
            {
                "exclude": false,
                "record_id": "ba-01-n-9096"
            }
        ],
        "value": 8.97216370739051e-07
    },
    "Ar38": {
        "error": 2.665819245199877e-07,
        "error_type": "",
        "fit": "previous",
        "references": [
            {
                "exclude": false,
                "record_id": "ba-01-n-9096"
            }
        ],
        "value": 4.1016488575544444e-07
    },
    "Ar39": {
        "error": 4.1702102952252445e-07,
        "error_type": "",
        "fit": "previous",
        "references": [
            {
                "exclude": false,
                "record_id": "ba-01-n-9096"
            }
        ],
        "value": 2.8887517659442448e-08
    },
    "Ar40": {
        "error": 3.859999140299341e-06,
        "error_type": "",
        "fit": "previous",
        "references": [
            {
                "exclude": false,
                "record_id": "ba-01-n-9096"
            }
        ],
        "value": 0.00010548380828363077
    }
}