{
    "baselines": [
        {
            "blob": "Qkf0VDedUM9CcKMyN5TdZUKMlYA3lxpN",
            "detector": "H3"
        },
        {
            "blob": "Qkf0VLfanxhCcKMyt8vTDUKMlYC3onA6",
            "detector": "H1"
        },
        {
            "blob": "Qkf0VLh+pcRCcKMyuITfO0KMlYC4g7nT",
            "detector": "L1"
        },
        {
            "blob": "Qkf0VLdrM2pCcKMyt3S4xUKMlYC3fq9x",
            "detector": "L3"
        },
        {
            "blob": "Qkf0VLvvYJFCcKMyu+9uf0KMlYC772gj",
            "detector": "L5"
        }
    ],
    "commit": "7e34bc2bccf056ad74a77d9797ac0a56631bb39d",
    "encoding": "base64",
    "format": ">ff",
    "signals": [
        {
            "blob": "Qbmxez7z+YpCCN8EPvHvRw==",
            "detector": "H3",
            "isotope": "Ar40"
        },
        {
            "blob": "Qbmxe7eeN29CCN8EtmN3xg==",
            "detector": "H1",
            "isotope": "Ar39"
        },
        {
            "blob": "QbmxezlyWJBCCN8EOXFyww==",
            "detector": "L1",
            "isotope": "Ar38"
        },
        {
            "blob": "Qbmxe7czgPBCCN8Etpdqkg==",
            "detector": "L3",
            "isotope": "Ar37"
        },
        {
            "blob": "Qbmxe7u9qNxCCN8Eu73aNw==",
            "detector": "L5",
            "isotope": "Ar36"
        }
    ],
    "sniffs": [
        {
            "blob": null,
            "detector": "H3",
            "isotope": "Ar40"
        },
        {
            "blob": null,
            "detector": "H1",
            "isotope": "Ar39"
        },
        {
            "blob": null,
            "detector": "L1",
            "isotope": "Ar38"
        },
        {
            "blob": null,
            "detector": "L3",
            "isotope": "Ar37"
        },
        {
            "blob": null,
            "detector": "L5",
            "isotope": "Ar36"
        }
    ]
}