{
    "Ar36": {
        "error": 4.024962367764546e-07,
        "error_type": "",
        "fit": "previous",
        "references": [
            {
                "exclude": false,
                "record_id": "ba-01-n-9639"
            }
        ],
        "value": -6.202010707379718e-07
    },
    "Ar37": {
        "error": 2.4894867780021466e-07,
        "error_type": "",
        "fit": "previous",
        "references": [
            {
                "exclude": false,
                "record_id": "ba-01-n-9639"
            }
        ],
        "value": 2.9824735406981796e-07
    },
    "Ar38": {
        "error": 2.6842374800206375e-07,
        "error_type": "",
        "fit": "previous",
        "references": [
            {
                "exclude": false,
                "record_id": "ba-01-n-9639"
            }
        ],
        "value": -6.11742015037804e-07
    },
    "Ar39": {
        "error": 2.68324114259876e-07,
        "error_type": "",
        "fit": "previous",
        "references": [
            {
                "exclude": false,
                "record_id": "ba-01-n-9639"
            }
        ],
        "value": 9.141317767310863e-08
    },
    "Ar40": {
        "error": 3.2889431262391423e-06,
        "error_type": "",
        "fit": "previous",
        "references": [
            {
                "exclude": false,
                "record_id": "ba-01-n-9639"
            }
        ],
        "value": 2.1861420805497408e-05
    }
}