{
    "Ar36": {
        "error": 2.723510670592565e-07,
        "error_type": "",
        "fit": "previous",
        "references": [
            {
                "exclude": false,
                "record_id": "ba-01-n-9413"
            }
        ],
        "value": -2.9083730303516506e-06
    },
    "Ar37": {
        "error": 2.2081321841085013e-07,
        "error_type": "",
        "fit": "previous",
        "references": [
            {
                "exclude": false,
                "record_id": "ba-01-n-9413"
            }
        ],
        "value": 3.752167594718987e-07
    },
    "Ar38": {
        "error": 2.2247815026386776e-07,
        "error_type": "",
        "fit": "previous",
        "references": [
            {
                "exclude": false,
                "record_id": "ba-01-n-9413"
            }
        ],
        "value": -6.318541238122465e-08
    },
    "Ar39": {
        "error": 2.9131312529170527e-07,
        "error_type": "",
        "fit": "previous",
        "references": [
            {
                "exclude": false,
                "record_id": "ba-01-n-9413"
            }
        ],
        "value": 1.7171383188468385e-07
    },
    "Ar40": {
        "error": 3.4596931121990495e-06,
        "error_type": "",
        "fit": "previous",
        "references": [
            {
                "exclude": false,
                "record_id": "ba-01-n-9413"
            }
        ],
        "value": 4.18127698534053e-05
    }
}