{
    "Ar36": {
        "error": 1.685369806992605e-08,
        "error_type": "",
        "fit": "previous",
        "references": [
            {
                "exclude": false,
                "record_id": "ba-01-n-9632"
            }
        ],
        "value": 4.4440224482308984e-07
    },
    "Ar37": {
        "error": 2.2375627354582307e-07,
        "error_type": "",
        "fit": "previous",
        "references": [
            {
                "exclude": false,
                "record_id": "ba-01-n-9632"
            }
        ],
        "value": 2.1941595589687356e-07
    },
    "Ar38": {
        "error": 2.5002634442597276e-07,
        "error_type": "",
        "fit": "previous",
        "references": [
            {
                "exclude": false,
                "record_id": "ba-01-n-9632"
            }
        ],
        "value": 2.2808892741112835e-07
    },
    "Ar39": {
        "error": 2.96134908725001e-07,
        "error_type": "",
        "fit": "previous",
        "references": [
            {
                "exclude": false,
                "record_id": "ba-01-n-9632"
            }
        ],
        "value": 4.2769323627315603e-07
    },
    "Ar40": {
        "error": 2.214165876617236e-06,
        "error_type": "",
        "fit": "previous",
        "references": [
            {
                "exclude": false,
                "record_id": "ba-01-n-9632"
            }
        ],
        "value": 0.00011924860424576648
    }
}