{
    "baselines": [
        {
            "blob": "Qkfn2LYdjDhCcKc4to6YpUKMmsu2F8y+",
            "detector": "H3"
        },
        {
            "blob": "Qkfn2LfLBp1CcKc4t7oENEKMmsu3rAqq",
            "detector": "H1"
        },
        {
            "blob": "Qkfn2LgKrF5CcKc4uAoUnEKMmsu4BxdU",
            "detector": "L1"
        },
        {
            "blob": "Qkfn2LVcyaZCcKc4tlrUL0KMmsu2TFQw",
            "detector": "L3"
        },
        {
            "blob": "Qkfn2LvpDcZCcKc4u+jyREKMmsu76QMD",
            "detector": "L5"
        }
    ],
    "commit": "0170bb1fda0e0ee1ba36b02e5cb0897ad9ac1ac4",
    "encoding": "base64",
    "format": ">ff",
    "signals": [
        {
            "blob": "Qblatj8+VqRCCLp4Pz02uA==",
            "detector": "H3",
            "isotope": "Ar40"
        },
        {
            "blob": "QblatrawqoNCCLp4NwDSJQ==",
            "detector": "H1",
            "isotope": "Ar39"
        },
        {
            "blob": "Qblatjm5zgZCCLp4Obhzag==",
            "detector": "L1",
            "isotope": "Ar38"
        },
        {
            "blob": "QblatrT68mZCCLp4NaOvfg==",
            "detector": "L3",
            "isotope": "Ar37"
        },
        {
            "blob": "QblatruneTZCCLp4u6e59A==",
            "detector": "L5",
            "isotope": "Ar36"
        }
    ],
    "sniffs": [
        {
            "blob": null,
            "detector": "H3",
            "isotope": "Ar40"
        },
        {
            "blob": null,
            "detector": "H1",
            "isotope": "Ar39"
        },
        {
            "blob": null,
            "detector": "L1",
            "isotope": "Ar38"
        },
        {
            "blob": null,
            "detector": "L3",
            "isotope": "Ar37"
        },
        {
            "blob": null,
            "detector": "L5",
            "isotope": "Ar36"
        }
    ]
}